README.rst
setup.py
fadapa/__init__.py
fadapa/fadapa.py
fadapa/release.py
fadapa.egg-info/PKG-INFO
fadapa.egg-info/SOURCES.txt
fadapa.egg-info/dependency_links.txt
fadapa.egg-info/top_level.txt
tests/__init__.py
tests/test_fadapa.py