Metadata-Version: 1.1
Name: fadapa
Version: 0.3.1
Summary: FAstqc DAta PArser - A minimal parser to parse FastQC output data in Python
Home-page: https://github.com/fadapa/fadapa
Author: Anand Reddy Pandikunta
Author-email: anand21nanda@gmail.com
License: UNKNOWN
Keywords: bioinformatics fastqc parsing
Platform: UNKNOWN
Classifier: Development Status :: 5 - Production/Stable
Classifier: Operating System :: MacOS :: MacOS X
Classifier: Operating System :: Microsoft :: Windows
Classifier: Operating System :: OS Independent
Classifier: Operating System :: POSIX
Classifier: Programming Language :: Python
Classifier: Programming Language :: Python :: 2.7
Classifier: Programming Language :: Python :: 3
Classifier: Programming Language :: Python :: 3.3
Classifier: Programming Language :: Python :: 3.4
Classifier: Intended Audience :: Developers
Classifier: Intended Audience :: Science/Research
Classifier: Topic :: Scientific/Engineering :: Bio-Informatics
Classifier: Topic :: Software Development :: Libraries :: Python Modules
Classifier: Topic :: Utilities
